{"nodes": [{"id": "outline_fedvt_paper", "label": "Feedlot Economics and Management: Visualization Tool Paper Outline", "file_type": "document", "source_file": "documents/processed/Paper Outline - Feedlot Economics and Management.docx (1).pdf", "source_location": "Page 1", "source_url": null, "captured_at": null, "author": "Shivam Kanodia", "contributor": null}, {"id": "outline_fedvt_breakeven", "label": "FEDVT Break-Even Analysis Output", "file_type": "document", "source_file": "documents/processed/Paper Outline - Feedlot Economics and Management.docx (1).pdf", "source_location": "Page 2", "source_url": null, "captured_at": null, "author": null, "contributor": null}, {"id": "outline_fedvt_sensitivity", "label": "FEDVT Sensitivity Analysis Visualization", "file_type": "document", "source_file": "documents/processed/Paper Outline - Feedlot Economics and Management.docx (1).pdf", "source_location": "Page 2", "source_url": null, "captured_at": null, "author": null, "contributor": null}, {"id": "outline_fedvt_scenarios", "label": "FEDVT Use-Case Scenarios (base case, high feed cost, disease outbreak)", "file_type": "document", "source_file": "documents/processed/Paper Outline - Feedlot Economics and Management.docx (1).pdf", "source_location": "Page 2", "source_url": null, "captured_at": null, "author": null, "contributor": null}], "edges": [{"source": "outline_fedvt_paper", "target": "lit_summaries_fedvt", "relation": "implements", "confidence": "EXTRACTED", "confidence_score": 1.0, "source_file": "documents/processed/Paper Outline - Feedlot Economics and Management.docx (1).pdf", "source_location": "Page 1", "weight": 1.0}, {"source": "outline_fedvt_paper", "target": "outline_fedvt_breakeven", "relation": "implements", "confidence": "EXTRACTED", "confidence_score": 1.0, "source_file": "documents/processed/Paper Outline - Feedlot Economics and Management.docx (1).pdf", "source_location": "Page 2", "weight": 1.0}, {"source": "outline_fedvt_paper", "target": "outline_fedvt_sensitivity", "relation": "implements", "confidence": "EXTRACTED", "confidence_score": 1.0, "source_file": "documents/processed/Paper Outline - Feedlot Economics and Management.docx (1).pdf", "source_location": "Page 2", "weight": 1.0}, {"source": "outline_fedvt_paper", "target": "outline_fedvt_scenarios", "relation": "implements", "confidence": "EXTRACTED", "confidence_score": 1.0, "source_file": "documents/processed/Paper Outline - Feedlot Economics and Management.docx (1).pdf", "source_location": "Page 2", "weight": 1.0}], "hyperedges": []}